README.md
setup.py
kobra/__init__.py
kobra/__main__.py
kobra/core.py
kobra.egg-info/PKG-INFO
kobra.egg-info/SOURCES.txt
kobra.egg-info/dependency_links.txt
kobra.egg-info/entry_points.txt
kobra.egg-info/top_level.txt